bill.py
shakespeare_insult-1.0.3.dist-info/METADATA
shakespeare_insult-1.0.3.dist-info/RECORD
shakespeare_insult-1.0.3.dist-info/WHEEL
shakespeare_insult-1.0.3.dist-info/top_level.txt
